ai_review/__init__.py
ai_review/config.py
ai_review/cli/__init__.py
ai_review/cli/main.py
ai_review/cli/commands/__init__.py
ai_review/cli/commands/run_clear_inline_review.py
ai_review/cli/commands/run_clear_summary_review.py
ai_review/cli/commands/run_context_review.py
ai_review/cli/commands/run_inline_reply_review.py
ai_review/cli/commands/run_inline_review.py
ai_review/cli/commands/run_review.py
ai_review/cli/commands/run_summary_reply_review.py
ai_review/cli/commands/run_summary_review.py
ai_review/clients/__init__.py
ai_review/clients/azure_devops/__init__.py
ai_review/clients/azure_devops/client.py
ai_review/clients/azure_devops/schema.py
ai_review/clients/azure_devops/tools.py
ai_review/clients/azure_devops/pr/__init__.py
ai_review/clients/azure_devops/pr/client.py
ai_review/clients/azure_devops/pr/types.py
ai_review/clients/azure_devops/pr/schema/__init__.py
ai_review/clients/azure_devops/pr/schema/files.py
ai_review/clients/azure_devops/pr/schema/pull_request.py
ai_review/clients/azure_devops/pr/schema/threads.py
ai_review/clients/azure_devops/pr/schema/user.py
ai_review/clients/azure_openai/__init__.py
ai_review/clients/azure_openai/client.py
ai_review/clients/azure_openai/schema.py
ai_review/clients/azure_openai/types.py
ai_review/clients/bedrock/__init__.py
ai_review/clients/bedrock/client.py
ai_review/clients/bedrock/schema.py
ai_review/clients/bedrock/types.py
ai_review/clients/bitbucket_cloud/__init__.py
ai_review/clients/bitbucket_cloud/client.py
ai_review/clients/bitbucket_cloud/tools.py
ai_review/clients/bitbucket_cloud/pr/__init__.py
ai_review/clients/bitbucket_cloud/pr/client.py
ai_review/clients/bitbucket_cloud/pr/types.py
ai_review/clients/bitbucket_cloud/pr/schema/__init__.py
ai_review/clients/bitbucket_cloud/pr/schema/comments.py
ai_review/clients/bitbucket_cloud/pr/schema/files.py
ai_review/clients/bitbucket_cloud/pr/schema/pull_request.py
ai_review/clients/bitbucket_cloud/pr/schema/user.py
ai_review/clients/bitbucket_server/__init__.py
xai_review-0.56.0.dist-info/licenses/LICENSE
xai_review-0.56.0.dist-info/METADATA
xai_review-0.56.0.dist-info/WHEEL
xai_review-0.56.0.dist-info/entry_points.txt
xai_review-0.56.0.dist-info/top_level.txt
xai_review-0.56.0.dist-info/RECORD
