Metadata-Version: 2.4
Name: xai-review
Version: 0.56.0
Summary: AI-powered code review tool for GitHub, GitLab, Bitbucket Cloud, Bitbucket Server, Azure DevOps and Gitea — built with LLMs like OpenAI, Claude, Gemini, Ollama, Bedrock, OpenRouter and Azure OpenAI
Author-email: Nikita Filonov <nikita.filonov@gmail.com>
Maintainer-email: Nikita Filonov <nikita.filonov@example.com>
License:                                  Apache License
Project-URL: Issues, https://github.com/Nikita-Filonov/ai-review/issues
Project-URL: Homepage, https://github.com/Nikita-Filonov/ai-review
Project-URL: Repository, https://github.com/Nikita-Filonov/ai-review
Keywords: ai,code review,llm,openai,claude,gemini,ollama,bedrock,openrouter,ci/cd,gitlab,github,gitea,bitbucket,bitbucket cloud,bitbucket server,azure,azure devops,azure openai
Classifier: Programming Language :: Python :: 3
Classifier: Programming Language :: Python :: 3.11
Classifier: Programming Language :: Python :: 3.12
Classifier: Intended Audience :: Developers
Classifier: Topic :: Software Development :: Quality Assurance
Classifier: Topic :: Software Development :: Testing
Classifier: License :: OSI Approved :: Apache Software License
Classifier: Operating System :: OS Independent
Requires-Python: >=3.11
License-File: LICENSE
Requires-Dist: typer
Requires-Dist: httpx
Requires-Dist: pyyaml
Requires-Dist: loguru
Requires-Dist: aiofiles
Requires-Dist: pydantic
Requires-Dist: pydantic-settings
Provides-Extra: test
Requires-Dist: pytest; extra == "test"
Requires-Dist: pytest-asyncio; extra == "test"
Dynamic: license-file
